{"commitInfo":{"timestamp":1692238520544,"operation":"WRITE","operationParameters":{"mode":"Overwrite","partitionBy":"[]"},"isolationLevel":"Serializable","isBlindAppend":false,"operationMetrics":{"numFiles":"4","numOutputRows":"4","numOutputBytes":"2925"},"engineInfo":"Apache-Spark/3.4.1 Delta-Lake/2.4.0","txnId":"ae2bd629-e1c0-40a5-9a26-ce13930d946b"}}
{"protocol":{"minReaderVersion":1,"minWriterVersion":2}}
{"metaData":{"id":"ff8d1fca-7c31-4785-a1ad-48c035036250","format":{"provider":"parquet","options":{}},"schemaString":"{\"type\":\"struct\",\"fields\":[{\"name\":\"id\",\"type\":\"integer\",\"nullable\":true,\"metadata\":{}},{\"name\":\"Department\",\"type\":\"string\",\"nullable\":true,\"metadata\":{}}]}","partitionColumns":[],"configuration":{},"createdTime":1692238519459}}
{"add":{"path":"part-00000-1c46d9e7-4698-4d1e-be80-ad4820ae9189-c000.snappy.parquet","partitionValues":{},"size":691,"modificationTime":1692238520149,"dataChange":true,"stats":"{\"numRecords\":1,\"minValues\":{\"id\":1,\"Department\":\"IT\"},\"maxValues\":{\"id\":1,\"Department\":\"IT\"},\"nullCount\":{\"id\":0,\"Department\":0}}"}}
{"add":{"path":"part-00001-1239b59d-3123-49a9-b365-06eb5de0e503-c000.snappy.parquet","partitionValues":{},"size":740,"modificationTime":1692238520185,"dataChange":true,"stats":"{\"numRecords\":1,\"minValues\":{\"id\":2,\"Department\":\"Marketing\"},\"maxValues\":{\"id\":2,\"Department\":\"Marketing\"},\"nullCount\":{\"id\":0,\"Department\":0}}"}}
{"add":{"path":"part-00002-f8a7c183-7631-4276-8ea2-50b06bc353ac-c000.snappy.parquet","partitionValues":{},"size":782,"modificationTime":1692238520193,"dataChange":true,"stats":"{\"numRecords\":1,\"minValues\":{\"id\":3,\"Department\":\"Human Resources\"},\"maxValues\":{\"id\":3,\"Department\":\"Human Resources\"},\"nullCount\":{\"id\":0,\"Department\":0}}"}}
{"add":{"path":"part-00003-bb4cac66-d000-4731-8b5d-2d98046c1d53-c000.snappy.parquet","partitionValues":{},"size":712,"modificationTime":1692238520005,"dataChange":true,"stats":"{\"numRecords\":1,\"minValues\":{\"id\":4,\"Department\":\"Sales\"},\"maxValues\":{\"id\":4,\"Department\":\"Sales\"},\"nullCount\":{\"id\":0,\"Department\":0}}"}}
