{"commitInfo":{"timestamp":1692235258876,"operation":"WRITE","operationParameters":{"mode":"Overwrite","partitionBy":"[]"},"readVersion":12,"isolationLevel":"Serializable","isBlindAppend":false,"operationMetrics":{"numFiles":"4","numOutputRows":"6","numOutputBytes":"11794"},"engineInfo":"Apache-Spark/3.4.1 Delta-Lake/2.4.0","txnId":"051d4492-36c3-49bb-b498-a2bcffbea7ac"}}
{"add":{"path":"part-00000-6d993974-7020-4518-91fa-875e380ab48a-c000.snappy.parquet","partitionValues":{},"size":2933,"modificationTime":1692235250099,"dataChange":true,"stats":"{\"numRecords\":1,\"minValues\":{\"id\":1,\"Op\":\"u\",\"firstname\":\"James\",\"middlename\":\"\",\"lastname\":\"Smith\",\"cod_entry\":\"36636\",\"gender\":\"M\",\"salary\":\"5000\",\"DepID\":1,\"CostCenter\":\"2222\",\"TimeStamp\":\"2023-03-13 14:52:15\"},\"maxValues\":{\"id\":1,\"Op\":\"u\",\"firstname\":\"James\",\"middlename\":\"\",\"lastname\":\"Smith\",\"cod_entry\":\"36636\",\"gender\":\"M\",\"salary\":\"5000\",\"DepID\":1,\"CostCenter\":\"2222\",\"TimeStamp\":\"2023-03-13 14:52:15\"},\"nullCount\":{\"id\":0,\"Op\":0,\"firstname\":0,\"middlename\":0,\"lastname\":0,\"cod_entry\":0,\"gender\":0,\"salary\":0,\"DepID\":0,\"CostCenter\":0,\"TimeStamp\":0}}"}}
{"add":{"path":"part-00001-d6761bbe-f025-4ef5-aec6-50e8ab873f59-c000.snappy.parquet","partitionValues":{},"size":2999,"modificationTime":1692235250099,"dataChange":true,"stats":"{\"numRecords\":2,\"minValues\":{\"id\":2,\"Op\":\"i\",\"firstname\":\"Michael\",\"middlename\":\"\",\"lastname\":\"\",\"cod_entry\":\"40288\",\"gender\":\"M\",\"salary\":\"3500\",\"DepID\":2,\"CostCenter\":\"3333\",\"TimeStamp\":\"2023-03-13 14:52:15\"},\"maxValues\":{\"id\":3,\"Op\":\"u\",\"firstname\":\"Robert\",\"middlename\":\"Rose\",\"lastname\":\"Williams\",\"cod_entry\":\"42114\",\"gender\":\"M\",\"salary\":\"4000\",\"DepID\":3,\"CostCenter\":\"4444\",\"TimeStamp\":\"2023-03-13 14:52:15\"},\"nullCount\":{\"id\":0,\"Op\":0,\"firstname\":0,\"middlename\":0,\"lastname\":0,\"cod_entry\":0,\"gender\":0,\"salary\":0,\"DepID\":0,\"CostCenter\":0,\"TimeStamp\":0}}"}}
{"add":{"path":"part-00002-0d62bfeb-a122-411f-aed4-edb7593a699c-c000.snappy.parquet","partitionValues":{},"size":2959,"modificationTime":1692235250099,"dataChange":true,"stats":"{\"numRecords\":1,\"minValues\":{\"id\":1,\"Op\":\"i\",\"firstname\":\"Maria\",\"middlename\":\"Anne\",\"lastname\":\"Jones\",\"cod_entry\":\"39192\",\"gender\":\"F\",\"salary\":\"3800\",\"DepID\":3,\"CostCenter\":\"5555\",\"TimeStamp\":\"2023-03-13 14:52:15\"},\"maxValues\":{\"id\":1,\"Op\":\"i\",\"firstname\":\"Maria\",\"middlename\":\"Anne\",\"lastname\":\"Jones\",\"cod_entry\":\"39192\",\"gender\":\"F\",\"salary\":\"3800\",\"DepID\":3,\"CostCenter\":\"5555\",\"TimeStamp\":\"2023-03-13 14:52:15\"},\"nullCount\":{\"id\":0,\"Op\":0,\"firstname\":0,\"middlename\":0,\"lastname\":0,\"cod_entry\":0,\"gender\":0,\"salary\":0,\"DepID\":0,\"CostCenter\":0,\"TimeStamp\":0}}"}}
{"add":{"path":"part-00003-50a889f1-e763-45b3-9b23-56c29503ae0e-c000.snappy.parquet","partitionValues":{},"size":2903,"modificationTime":1692235250099,"dataChange":true,"stats":"{\"numRecords\":2,\"minValues\":{\"id\":1,\"Op\":\"d\",\"firstname\":\"\",\"middlename\":\"\",\"lastname\":\"\",\"cod_entry\":\"\",\"gender\":\"\",\"salary\":\"-1\",\"DepID\":0,\"CostCenter\":\"0\",\"TimeStamp\":\"2023-03-13 14:52:15\"},\"maxValues\":{\"id\":2,\"Op\":\"u\",\"firstname\":\"Jon\",\"middlename\":\"\",\"lastname\":\"Mary\",\"cod_entry\":\"Brown\",\"gender\":\"F\",\"salary\":\"0\",\"DepID\":1,\"CostCenter\":\"6666\",\"TimeStamp\":\"2023-03-13 14:52:15\"},\"nullCount\":{\"id\":0,\"Op\":0,\"firstname\":0,\"middlename\":0,\"lastname\":0,\"cod_entry\":0,\"gender\":0,\"salary\":0,\"DepID\":0,\"CostCenter\":0,\"TimeStamp\":0}}"}}
{"remove":{"path":"part-00003-4b58ab11-734d-4186-8db7-9edc1121a1dd-c000.snappy.parquet","deletionTimestamp":1692235258836,"dataChange":true,"extendedFileMetadata":true,"partitionValues":{},"size":2903}}
{"remove":{"path":"part-00000-3c8539aa-db2b-48e8-bdeb-ab1dddc5d48d-c000.snappy.parquet","deletionTimestamp":1692235258838,"dataChange":true,"extendedFileMetadata":true,"partitionValues":{},"size":2933}}
{"remove":{"path":"part-00001-55a2fad7-e299-4cba-a96f-0e5ff54c07fe-c000.snappy.parquet","deletionTimestamp":1692235258838,"dataChange":true,"extendedFileMetadata":true,"partitionValues":{},"size":2999}}
{"remove":{"path":"part-00002-22c4c98e-9c8f-40de-aacc-b6f945b7a41e-c000.snappy.parquet","deletionTimestamp":1692235258838,"dataChange":true,"extendedFileMetadata":true,"partitionValues":{},"size":2959}}
